myth_hash/__init__.py
myth_hash/cli.py
myth_hash/core/__init__.py
myth_hash/core/character_data_loader.py
myth_hash/core/hash_util.py
myth_hash/core/words.py
myth_hash/data/character_nouns.json
myth_hash/data/personality_attributes.json
myth_hash/data/physical_attributes.json
myth_hash/py.typed
myth_hash-0.2.1.dist-info/LICENSE
myth_hash-0.2.1.dist-info/METADATA
myth_hash-0.2.1.dist-info/WHEEL
myth_hash-0.2.1.dist-info/entry_points.txt
myth_hash-0.2.1.dist-info/RECORD
