Metadata-Version: 2.3
Name: myth-hash
Version: 0.2.1
Summary: A tool for generating human-readable, multilingual fantasy character names based on input string hashes.
License: MIT
Author: Claas Flint
Author-email: claas.flint@gmail.com
Requires-Python: >=3.11,<4.0
Classifier: License :: OSI Approved :: MIT License
Classifier: Operating System :: OS Independent
Classifier: Programming Language :: Python :: 3
Classifier: Programming Language :: Python :: 3.11
Classifier: Programming Language :: Python :: 3.12
Classifier: Programming Language :: Python :: 3.13
Classifier: Programming Language :: Python :: 3.14
Classifier: Typing :: Typed
Project-URL: Homepage, https://github.com/cl445/myth-hash
Project-URL: Repository, https://github.com/cl445/myth-hash
